agrspy/__init__.py
agrspy/chinaaqi.py
agrspy-0.0.1.dist-info/LICENSE
agrspy-0.0.1.dist-info/METADATA
agrspy-0.0.1.dist-info/WHEEL
agrspy-0.0.1.dist-info/top_level.txt
agrspy-0.0.1.dist-info/RECORD
