Metadata-Version: 2.1
Name: agrspy
Version: 0.0.1
Summary: left blank
Home-page: https://github.com/soonyenju/arspy
Author: Songyan Zhu
Author-email: soonyenju@foxmail.com
License: MIT Licence
Keywords: air quality
Platform: any
